vidal/__init__.py
vidal/cutter.py
vidal-1.3.3.dist-info/METADATA
vidal-1.3.3.dist-info/WHEEL
vidal-1.3.3.dist-info/entry_points.txt
vidal-1.3.3.dist-info/top_level.txt
vidal-1.3.3.dist-info/RECORD
