Metadata-Version: 2.1
Name: vidal
Version: 1.3.3
Summary: Video To Images
Home-page: UNKNOWN
Author: Sang Pil Yoo
Author-email: ysp9714@gmail.com
License: UNKNOWN
Keywords: video,frames
Platform: UNKNOWN
Classifier: Programming Language :: Python :: 3.6
Classifier: Programming Language :: Python :: 3.7
Classifier: Programming Language :: Python :: 3.8
Requires-Python: >=3.6
Requires-Dist: opencv-python
Requires-Dist: tqdm
